__init__.py
edulib/__init__.py
"edulib/toolkit/__init__,py"
edulib/toolkit/filereader.py
edulib/toolkit/textcleaner.py
Edulib-0.0.1.dist-info/LICENSE
Edulib-0.0.1.dist-info/METADATA
Edulib-0.0.1.dist-info/WHEEL
Edulib-0.0.1.dist-info/top_level.txt
Edulib-0.0.1.dist-info/RECORD
